huawei_e3_e5/__init__.py
huawei_e3_e5/datastructures.py
huawei_e3_e5/huawei_db.py
huawei_e3_e5/huawei_exxxx.py
huawei_e3_e5/modem.py
huawei_e3_e5-0.1.5.dist-info/LICENSE
huawei_e3_e5-0.1.5.dist-info/METADATA
huawei_e3_e5-0.1.5.dist-info/WHEEL
huawei_e3_e5-0.1.5.dist-info/top_level.txt
huawei_e3_e5-0.1.5.dist-info/RECORD
