Metadata-Version: 2.1
Name: huawei-e3-e5
Version: 0.1.5
Summary: API For huawei LAN/WAN LTE Modems
Home-page: https://github.com/afer92/huawei_e3_e5
Author: Alain Ferraro
License: LGPL-3.0 
Platform: UNKNOWN
Classifier: Development Status :: 5 - Production/Stable
Classifier: Environment :: Console
Classifier: Intended Audience :: Developers
Classifier: License :: OSI Approved :: GNU Lesser General Public License v3 (LGPLv3)
Classifier: Operating System :: OS Independent
Classifier: Programming Language :: Python
Classifier: Programming Language :: Python :: 3
Classifier: Programming Language :: Python :: 3.4
Classifier: Programming Language :: Python :: 3.5
Classifier: Programming Language :: Python :: 3.6
Classifier: Programming Language :: Python :: 3.7
Classifier: Programming Language :: Python :: 3.8
Classifier: Topic :: Software Development
Requires-Python: >=3.4
Requires-Dist: dicttoxml
Requires-Dist: huawei-lte-api
Requires-Dist: requests
Requires-Dist: xmltodict
